icinga2confgen/ConfigBuilder.py
icinga2confgen/ValueChecker.py
icinga2confgen/ValueMapper.py
icinga2confgen/__init__.py
icinga2confgen/Checks/Check.py
icinga2confgen/Checks/__init__.py
icinga2confgen/Checks/ClaudioKuenzler/CheckESXIHardware.py
icinga2confgen/Checks/ClaudioKuenzler/CheckStorcenter.py
icinga2confgen/Checks/ClaudioKuenzler/__init__.py
icinga2confgen/Checks/HariSekhonNagiosPlugins/CheckYum.py
icinga2confgen/Checks/HariSekhonNagiosPlugins/__init__.py
icinga2confgen/Checks/MonitoringPlugins/CheckCiphers.py
icinga2confgen/Checks/MonitoringPlugins/CheckDNSSECExpire.py
icinga2confgen/Checks/MonitoringPlugins/CheckDS18B20.py
icinga2confgen/Checks/MonitoringPlugins/CheckDenyTlsVersion.py
icinga2confgen/Checks/MonitoringPlugins/CheckDockerLogin.py
icinga2confgen/Checks/MonitoringPlugins/CheckExistingUsers.py
icinga2confgen/Checks/MonitoringPlugins/CheckGroupMembers.py
icinga2confgen/Checks/MonitoringPlugins/CheckOpenPorts.py
icinga2confgen/Checks/MonitoringPlugins/CheckPageContent.py
icinga2confgen/Checks/MonitoringPlugins/CheckPathExists.py
icinga2confgen/Checks/MonitoringPlugins/CheckRebootRequired.py
icinga2confgen/Checks/MonitoringPlugins/CheckSPF.py
icinga2confgen/Checks/MonitoringPlugins/CheckSSHDSecurity.py
icinga2confgen/Checks/MonitoringPlugins/CheckUFWStatus.py
icinga2confgen/Checks/MonitoringPlugins/__init__.py
icinga2confgen/Checks/MonitoringPlugins/SNMP/CheckSNMP.py
icinga2confgen/Checks/MonitoringPlugins/SNMP/__init__.py
icinga2confgen/Checks/MonitoringPlugins/SNMP/PowerNet_MIB/CheckBatteryBadBatteryPacks.py
icinga2confgen/Checks/MonitoringPlugins/SNMP/PowerNet_MIB/CheckBatteryCapacity.py
icinga2confgen/Checks/MonitoringPlugins/SNMP/PowerNet_MIB/CheckBatteryPacksAttached.py
icinga2confgen/Checks/MonitoringPlugins/SNMP/PowerNet_MIB/CheckBatteryRemainingRuntime.py
icinga2confgen/Checks/MonitoringPlugins/SNMP/PowerNet_MIB/CheckBatteryReplacement.py
icinga2confgen/Checks/MonitoringPlugins/SNMP/PowerNet_MIB/CheckBatteryStatus.py
icinga2confgen-0.0.8.post2.dist-info/LICENSE
icinga2confgen-0.0.8.post2.dist-info/METADATA
icinga2confgen-0.0.8.post2.dist-info/WHEEL
icinga2confgen-0.0.8.post2.dist-info/top_level.txt
icinga2confgen-0.0.8.post2.dist-info/RECORD
