Metadata-Version: 2.1
Name: icinga2confgen
Version: 0.0.8.post2
Summary: Icinga2 configuration file generator for hosts, commands, checks, ... in python
Home-page: https://github.com/f-froehlich/icinga2-config-generator
Author: Fabian Fröhlich
Author-email: mail@confgen.org
License: AGPLv3
Download-URL: https://pypi.org/project/icinga2confgen/
Keywords: icinga,icinga2,icinga2-configuration,icinga2-plugin,configuration,configuration-management,monitoring,check,nagios,nagios-plugin,nrpe,healthcheck,serverstatus,security,security-tools
Platform: UNKNOWN
Requires-Dist: tqdm
